entityframe-0.1.10.dist-info/RECORD
entityframe-0.1.10.dist-info/WHEEL
entityframe-0.1.10.dist-info/METADATA
entityframe-0.1.10.dist-info/licenses/LICENSE
entityframe/entityframe.cpython-311-darwin.so
entityframe/__init__.py
entityframe/frame.py
entityframe/collection.py
entityframe/entity.py
